{

  "Steganography": [
    {
      "name": "zsteg",
      "command": "zsteg",
      "mode": "file",
      "description": "Detect hidden data in PNG and BMP",
      "options": []
    },
    {
      "name": "zbarimg",
      "command": "zbarimg",
      "mode": "file",
      "description": "Scan barcodes or QR codes in images",
      "options": []
    },
    {
      "name": "steghide",
      "command": "steghide",
      "mode": "file",
      "description": "Extract hidden data from stego files",
      "options": []
    }
  ],

  "Forensics": [
    {
      "name": "binwalk",
      "command": "binwalk",
      "mode": "file",
      "description": "Analyze binary files for embedded data",
      "options": []
    },
    {
      "name": "foremost",
      "command": "foremost",
      "mode": "file",
      "description": "Recover files using headers",
      "options": [
        {
          "flag": "-i",
          "type": "file",
          "description": "Input file"
        }
      ]
    },
    {
      "name": "exiftool",
      "command": "exiftool",
      "mode": "file",
      "description": "Read metadata from files",
      "options": []
    },
    {
      "name": "tshark",
      "command": "tshark",
      "mode": "file",
      "description": "Analyze packet capture files",
      "options": [
        {
          "flag": "-r",
          "type": "file",
          "description": "Read packet capture file"
        }
      ]
    }
  ],

  "Cryptography": [
    {
      "name": "base64_decode",
      "command": "base64",
      "mode": "text",
      "description": "Decode Base64 data",
      "options": [
        {
          "flag": "-d",
          "type": "checkbox",
          "description": "Decode mode"
        },
        {
          "flag": "-i",
          "type": "checkbox",
          "description": "Ignore invalid characters"
        }
      ]
    },
    {
      "name": "base32_decode",
      "command": "base32",
      "mode": "text",
      "description": "Decode Base32 data",
      "options": [
        {
          "flag": "-d",
          "type": "checkbox",
          "description": "Decode mode"
        }
      ]
    },
    {
      "name": "rot13",
      "command": "tr",
      "mode": "text",
      "description": "ROT13 transformation",
      "options": []
    },
    {
      "name": "hex_decode",
      "command": "xxd",
      "mode": "text",
      "description": "Decode hex to binary",
      "options": [
        {
          "flag": "-r",
          "type": "checkbox",
          "description": "Reverse hex dump"
        },
        {
          "flag": "-p",
          "type": "checkbox",
          "description": "Plain hex format"
        }
      ]
    },
    {
      "name": "reverse",
      "command": "rev",
      "mode": "text",
      "description": "Reverse text lines",
      "options": []
    }
  ],

  "Pwnable": [
    {
      "name": "checksec",
      "command": "checksec",
      "mode": "file",
      "description": "Check binary security protections",
      "options": []
    },
    {
      "name": "file",
      "command": "file",
      "mode": "file",
      "description": "Determine file type",
      "options": []
    },
    {
      "name": "md5sum",
      "command": "md5sum",
      "mode": "file",
      "description": "Generate MD5 hash",
      "options": []
    }
  ],

  "Mobile Security": [
    {
      "name": "apktool",
      "command": "apktool",
      "mode": "file",
      "description": "Reverse engineer Android APK",
      "options": [
        {
          "flag": "d",
          "type": "checkbox",
          "description": "Decode APK"
        }
      ]
    },
    {
      "name": "jadx",
      "command": "jadx",
      "mode": "file",
      "description": "Decompile Android APK",
      "options": []
    },
    {
      "name": "dex_strings",
      "command": "strings",
      "mode": "file",
      "description": "Extract strings from DEX file",
      "options": []
    }
  ],

  "Programming": [
    {
      "name": "grep",
      "command": "grep",
      "mode": "text",
      "description": "Search text using patterns",
      "options": [
        {
          "flag": "-n",
          "type": "checkbox",
          "description": "Show line numbers"
        },
        {
          "flag": "-v",
          "type": "checkbox",
          "description": "Invert match"
        },
        {
          "flag": "",
          "type": "text",
          "placeholder": "Search pattern"
        }
      ]
    }
  ],

  "Reverse Engineering": [
    {
      "name": "strings",
      "command": "strings",
      "mode": "file",
      "description": "Extract printable strings from binaries",
      "options": [
        {
          "flag": "-n",
          "type": "text",
          "placeholder": "Minimum string length"
        }
      ]
    }
  ]
}